cremdock/__init__.py
cremdock/arg_types.py
cremdock/auxiliary.py
cremdock/crem_grow.py
cremdock/cremdock.py
cremdock/database.py
cremdock/molecules.py
cremdock/ranking.py
cremdock/selection.py
cremdock/user_protected_atoms.py
cremdock/scripts/__init__.py
cremdock/scripts/arg_types.py
cremdock/scripts/plif.py
cremdock-0.2.0.dist-info/LICENSE
cremdock-0.2.0.dist-info/METADATA
cremdock-0.2.0.dist-info/WHEEL
cremdock-0.2.0.dist-info/entry_points.txt
cremdock-0.2.0.dist-info/top_level.txt
cremdock-0.2.0.dist-info/RECORD
