Metadata-Version: 2.1
Name: cremdock
Version: 0.2.0
Summary: CReM-dock: molecule generation and decoration guided by molecular docking
Home-page: https://github.com/ci-lab-cz/crem-dock
Author: Guzel Minibaeva, Pavel Polishchuk
Author-email: pavel_polishchuk@ukr.net
Classifier: Programming Language :: Python :: 3
Classifier: License :: OSI Approved :: GNU General Public License v3 (GPLv3)
Classifier: Operating System :: POSIX :: Linux
Classifier: Topic :: Scientific/Engineering :: Bio-Informatics
Classifier: Topic :: Scientific/Engineering :: Chemistry
Requires-Python: >=3.9
License-File: LICENSE
Provides-Extra: crem
Requires-Dist: crem >=0.2.14 ; extra == 'crem'
Provides-Extra: easydock
Requires-Dist: easydock >=1.0 ; extra == 'easydock'
Provides-Extra: rdkit
Requires-Dist: rdkit >=2017.09 ; extra == 'rdkit'
